XLRP/__init__.py
XLRP/drawplot.py
XLRP/xl_ddt.py
XLRP/xl_logger.py
XLRP/xlconf.py
XLRP/xlrp.py
xlrp-0.5.4.dist-info/LICENSE.txt
xlrp-0.5.4.dist-info/METADATA
xlrp-0.5.4.dist-info/WHEEL
xlrp-0.5.4.dist-info/top_level.txt
xlrp-0.5.4.dist-info/RECORD
