Metadata-Version: 2.1
Name: xlrp
Version: 0.5.4
Summary: 生成excel测试报告
Home-page: 
Author: 测码范晔
Author-email: 1538379200@qq.com
License: UNKNOWN
Platform: UNKNOWN
Classifier: Programming Language :: Python :: 3
Classifier: License :: OSI Approved :: MIT License
Classifier: Operating System :: OS Independent
License-File: LICENSE.txt
Requires-Dist: numpy (>=1.22.3)
Requires-Dist: matplotlib (>=3.5.1)
Requires-Dist: openpyxl (>=3.0.9)
Requires-Dist: pywin32
